daxus/__init__.py
daxus/_daxus.py
daxus-1.0.post1.dist-info/LICENSE
daxus-1.0.post1.dist-info/WHEEL
daxus-1.0.post1.dist-info/METADATA
daxus-1.0.post1.dist-info/RECORD
